ctail/__init__.py
ctail/colors.py
ctail/main.py
ctail-0.0.3.data/scripts/ctail
ctail-0.0.3.dist-info/LICENSE
ctail-0.0.3.dist-info/METADATA
ctail-0.0.3.dist-info/WHEEL
ctail-0.0.3.dist-info/top_level.txt
ctail-0.0.3.dist-info/RECORD
