Metadata-Version: 2.1
Name: ctail
Version: 0.0.3
Summary: A colored tail
Home-page: https://github.com/otger/ctail
Author: Otger Ballester
Author-email: otger@gmail.com
License: UNKNOWN
Project-URL: Bug Tracker, https://github.com/otger/ctail/issues
Platform: UNKNOWN
Classifier: Programming Language :: Python :: 3
Classifier: License :: OSI Approved :: MIT License
Classifier: Operating System :: OS Independent
Requires-Python: >=3.6
License-File: LICENSE
